pynlo/__init__.py
pynlo/devices/grating_compressor.py
pynlo/devices/__init__.py
pynlo/interactions/__init__.py
pynlo/interactions/FourWaveMixing/getGainsForGNLSE.py
pynlo/interactions/FourWaveMixing/global_variables.py
pynlo/interactions/FourWaveMixing/SSFM.py
pynlo/interactions/FourWaveMixing/__init__.py
pynlo/interactions/ThreeWaveMixing/DFG.py
pynlo/interactions/ThreeWaveMixing/DFG_integrand.py
pynlo/interactions/ThreeWaveMixing/dfg_problem.py
pynlo/interactions/ThreeWaveMixing/field_classes.py
pynlo/interactions/ThreeWaveMixing/multi_run_rw.py
pynlo/interactions/ThreeWaveMixing/__init__.py
pynlo/light/beam.py
pynlo/light/DerivedPulses.py
pynlo/light/PulseBase.py
pynlo/light/__init__.py
pynlo/media/__init__.py
pynlo/media/crystals/Boyd.py
pynlo/media/crystals/CrystalContainer.py
pynlo/media/crystals/PPLN.py
pynlo/media/crystals/PPLN_temperature_independent.py
pynlo/media/crystals/XTAL_AgGaS.py
pynlo/media/crystals/XTAL_AgGaSe2.py
pynlo/media/crystals/XTAL_PPLN.py
pynlo/media/crystals/__init__.py
pynlo/media/fibers/calculators.py
pynlo/media/fibers/fiber.py
pynlo/media/fibers/fiber_config.txt
pynlo/media/fibers/general_fibers.txt
pynlo/media/fibers/JSONFiberLoader.py
pynlo/media/fibers/__init__.py
pynlo/util/pynlo_ffts.py
pynlo/util/__init__.py
pynlo/util/Calculators/DispersiveWave_ResonancerFrequency.py
pynlo/util/ode_solve/dopr853.py
pynlo/util/ode_solve/dopr853_constants.py
pynlo/util/ode_solve/dopr853_controller.py
pynlo/util/ode_solve/example.py
pynlo/util/ode_solve/steppers.py
pynlo/util/ode_solve/test.py
pynlo/util/ode_solve/__init__.py
pyNLO-0.1.dist-info/DESCRIPTION.rst
pyNLO-0.1.dist-info/METADATA
pyNLO-0.1.dist-info/metadata.json
pyNLO-0.1.dist-info/RECORD
pyNLO-0.1.dist-info/top_level.txt
pyNLO-0.1.dist-info/WHEEL
