Metadata-Version: 2.0
Name: pyNLO
Version: 0.1
Summary: Python nonlinear optics
Home-page: https://github.com/ycasg/PyNLO
Author: Gabe Ycas
Author-email: ycasg@colorado.edu
License: UNKNOWN
Platform: UNKNOWN
Requires-Dist: jsonpickle (>=0.9.2)
Requires-Dist: jsonschema (>=2.5.1)
Requires-Dist: lxml (>=3.4.4)
Requires-Dist: mock (>=1.0.1)
Requires-Dist: nose (>=1.3.7)
Requires-Dist: nose-cov (>=1.6)
Requires-Dist: nose-fixes (>=1.3)
Requires-Dist: numpy (>=1.9.2)
Requires-Dist: pyFFTW (>=0.9.0)
Requires-Dist: scipy (>=0.15.1)
Requires-Dist: unittest2 (>=1.0.1)
